{
  "$schema": "https://raw.githubusercontent.com/nuke-build/nuke/master/source/Nuke.CodeGeneration/schema.json",
  "license": [
    "Copyright Sebastian Karasek, Matthias Koch 2018.",
    "Distributed under the MIT License.",
    "https://github.com/nuke-build/azure/blob/master/LICENSE"
  ],
  "references": [
    "https://raw.githubusercontent.com/Azure/azure-docs-cli-python/67b9fd6/latest/docs-ref-autogen/lab.yml",
    "https://raw.githubusercontent.com/Azure/azure-docs-cli-python/67b9fd6/latest/docs-ref-autogen/lab/custom-image.yml",
    "https://raw.githubusercontent.com/Azure/azure-docs-cli-python/67b9fd6/latest/docs-ref-autogen/lab/environment.yml",
    "https://raw.githubusercontent.com/Azure/azure-docs-cli-python/67b9fd6/latest/docs-ref-autogen/lab/artifact-source.yml",
    "https://raw.githubusercontent.com/Azure/azure-docs-cli-python/67b9fd6/latest/docs-ref-autogen/lab/vnet.yml",
    "https://raw.githubusercontent.com/Azure/azure-docs-cli-python/67b9fd6/latest/docs-ref-autogen/lab/secret.yml",
    "https://raw.githubusercontent.com/Azure/azure-docs-cli-python/67b9fd6/latest/docs-ref-autogen/lab/artifact.yml",
    "https://raw.githubusercontent.com/Azure/azure-docs-cli-python/67b9fd6/latest/docs-ref-autogen/lab/arm-template.yml",
    "https://raw.githubusercontent.com/Azure/azure-docs-cli-python/67b9fd6/latest/docs-ref-autogen/lab/vm.yml",
    "https://raw.githubusercontent.com/Azure/azure-docs-cli-python/67b9fd6/latest/docs-ref-autogen/lab/gallery-image.yml",
    "https://raw.githubusercontent.com/Azure/azure-docs-cli-python/67b9fd6/latest/docs-ref-autogen/lab/formula.yml"
  ],
  "name": "AzureLab",
  "officialUrl": "https://docs.microsoft.com/en-us/cli/azure/lab?view=azure-cli-latest",
  "help": "Manage Azure DevTest Labs.",
  "pathExecutable": "az",
  "tasks": [
    {
      "postfix": "Delete",
      "definiteArgument": "lab delete",
      "settingsClass": {
        "properties": [
          {
            "name": "Name",
            "type": "string",
            "format": "--name {value}",
            "help": "The name of the lab."
          },
          {
            "name": "ResourceGroup",
            "type": "string",
            "format": "--resource-group {value}",
            "help": "Name of resource group. You can configure the default group using `az configure --defaults group=&amp;lt;name&amp;gt;`."
          }
        ]
      }
    },
    {
      "postfix": "Get",
      "definiteArgument": "lab get",
      "settingsClass": {
        "properties": [
          {
            "name": "Name",
            "type": "string",
            "format": "--name {value}",
            "help": "The name of the lab."
          },
          {
            "name": "ResourceGroup",
            "type": "string",
            "format": "--resource-group {value}",
            "help": "Name of resource group. You can configure the default group using `az configure --defaults group=&amp;lt;name&amp;gt;`."
          },
          {
            "name": "Expand",
            "type": "string",
            "format": "--expand {value}",
            "help": "Specify the $expand query. Example: 'properties($select=defaultStorageAccount)'."
          }
        ]
      }
    },
    {
      "postfix": "CustomImageCreate",
      "definiteArgument": "lab custom-image create",
      "settingsClass": {
        "properties": [
          {
            "name": "LabName",
            "type": "string",
            "format": "--lab-name {value}",
            "help": "Name of the Lab."
          },
          {
            "name": "Name",
            "type": "string",
            "format": "--name {value}",
            "help": "Name of the image."
          },
          {
            "name": "OsState",
            "type": "string",
            "format": "--os-state {value}",
            "help": "The current state of the virtual machine."
          },
          {
            "name": "OsType",
            "type": "string",
            "format": "--os-type {value}",
            "help": "Type of the OS on which the custom image is based. Allowed values are: Windows, Linux."
          },
          {
            "name": "ResourceGroup",
            "type": "string",
            "format": "--resource-group {value}",
            "help": "Name of resource group. You can configure the default group using `az configure --defaults group=&amp;lt;name&amp;gt;`."
          },
          {
            "name": "SourceVmId",
            "type": "string",
            "format": "--source-vm-id {value}",
            "help": "The resource ID of a virtual machine in the provided lab."
          },
          {
            "name": "Author",
            "type": "string",
            "format": "--author {value}",
            "help": "The author of the custom image."
          },
          {
            "name": "Description",
            "type": "string",
            "format": "--description {value}",
            "help": "A detailed description for the custom image."
          }
        ]
      }
    },
    {
      "postfix": "CustomImageDelete",
      "definiteArgument": "lab custom-image delete",
      "settingsClass": {
        "properties": [
          {
            "name": "LabName",
            "type": "string",
            "format": "--lab-name {value}",
            "help": "The name of the lab."
          },
          {
            "name": "Name",
            "type": "string",
            "format": "--name {value}",
            "help": "The name of the custom image."
          },
          {
            "name": "ResourceGroup",
            "type": "string",
            "format": "--resource-group {value}",
            "help": "Name of resource group. You can configure the default group using `az configure --defaults group=&amp;lt;name&amp;gt;`."
          }
        ]
      }
    },
    {
      "postfix": "CustomImageList",
      "definiteArgument": "lab custom-image list",
      "settingsClass": {
        "properties": [
          {
            "name": "LabName",
            "type": "string",
            "format": "--lab-name {value}",
            "help": "The name of the lab."
          },
          {
            "name": "ResourceGroup",
            "type": "string",
            "format": "--resource-group {value}",
            "help": "Name of resource group. You can configure the default group using `az configure --defaults group=&amp;lt;name&amp;gt;`."
          },
          {
            "name": "Expand",
            "type": "string",
            "format": "--expand {value}",
            "help": "Specify the $expand query. Example: 'properties($select=vm)'."
          },
          {
            "name": "Filter",
            "type": "string",
            "format": "--filter {value}",
            "help": "The filter to apply to the operation."
          },
          {
            "name": "Orderby",
            "type": "string",
            "format": "--orderby {value}",
            "help": "The ordering expression for the results, using OData notation."
          },
          {
            "name": "Top",
            "type": "int",
            "format": "--top {value}",
            "help": "The maximum number of resources to return from the operation."
          }
        ]
      }
    },
    {
      "postfix": "CustomImageShow",
      "definiteArgument": "lab custom-image show",
      "settingsClass": {
        "properties": [
          {
            "name": "LabName",
            "type": "string",
            "format": "--lab-name {value}",
            "help": "The name of the lab."
          },
          {
            "name": "Name",
            "type": "string",
            "format": "--name {value}",
            "help": "The name of the custom image."
          },
          {
            "name": "ResourceGroup",
            "type": "string",
            "format": "--resource-group {value}",
            "help": "Name of resource group. You can configure the default group using `az configure --defaults group=&amp;lt;name&amp;gt;`."
          },
          {
            "name": "Expand",
            "type": "string",
            "format": "--expand {value}",
            "help": "Specify the $expand query. Example: 'properties($select=vm)'."
          }
        ]
      }
    },
    {
      "postfix": "EnvironmentCreate",
      "definiteArgument": "lab environment create",
      "settingsClass": {
        "properties": [
          {
            "name": "ArmTemplate",
            "type": "string",
            "format": "--arm-template {value}",
            "help": "Name or ID of the ARM template in the lab."
          },
          {
            "name": "LabName",
            "type": "string",
            "format": "--lab-name {value}",
            "help": "Name of the lab."
          },
          {
            "name": "Name",
            "type": "string",
            "format": "--name {value}",
            "help": "Name of the environment."
          },
          {
            "name": "ResourceGroup",
            "type": "string",
            "format": "--resource-group {value}",
            "help": "Name of the lab's resource group."
          },
          {
            "name": "ArtifactSourceName",
            "type": "string",
            "format": "--artifact-source-name {value}",
            "help": "Name of the artifact source in the lab."
          },
          {
            "name": "Parameters",
            "type": "string",
            "format": "--parameters {value}",
            "help": "JSON encoded list of parameters. Use '@{file}' to load from a file."
          },
          {
            "name": "Tags",
            "type": "string",
            "format": "--tags {value}",
            "help": "The tags for the resource."
          }
        ]
      }
    },
    {
      "postfix": "EnvironmentDelete",
      "definiteArgument": "lab environment delete",
      "settingsClass": {
        "properties": [
          {
            "name": "LabName",
            "type": "string",
            "format": "--lab-name {value}",
            "help": "The name of the lab."
          },
          {
            "name": "Name",
            "type": "string",
            "format": "--name {value}",
            "help": "The name of the environment."
          },
          {
            "name": "ResourceGroup",
            "type": "string",
            "format": "--resource-group {value}",
            "help": "Name of resource group. You can configure the default group using `az configure --defaults group=&amp;lt;name&amp;gt;`."
          }
        ]
      }
    },
    {
      "postfix": "EnvironmentList",
      "definiteArgument": "lab environment list",
      "settingsClass": {
        "properties": [
          {
            "name": "LabName",
            "type": "string",
            "format": "--lab-name {value}",
            "help": "The name of the lab."
          },
          {
            "name": "ResourceGroup",
            "type": "string",
            "format": "--resource-group {value}",
            "help": "Name of resource group. You can configure the default group using `az configure --defaults group=&amp;lt;name&amp;gt;`."
          },
          {
            "name": "Expand",
            "type": "string",
            "format": "--expand {value}",
            "help": "Specify the $expand query. Example: 'properties($select=deploymentProperties)'."
          },
          {
            "name": "Filter",
            "type": "string",
            "format": "--filter {value}",
            "help": "The filter to apply to the operation."
          },
          {
            "name": "Orderby",
            "type": "string",
            "format": "--orderby {value}",
            "help": "The ordering expression for the results, using OData notation."
          },
          {
            "name": "Top",
            "type": "int",
            "format": "--top {value}",
            "help": "The maximum number of resources to return from the operation."
          }
        ]
      }
    },
    {
      "postfix": "EnvironmentShow",
      "definiteArgument": "lab environment show",
      "settingsClass": {
        "properties": [
          {
            "name": "LabName",
            "type": "string",
            "format": "--lab-name {value}",
            "help": "The name of the lab."
          },
          {
            "name": "Name",
            "type": "string",
            "format": "--name {value}",
            "help": "The name of the environment."
          },
          {
            "name": "ResourceGroup",
            "type": "string",
            "format": "--resource-group {value}",
            "help": "Name of resource group. You can configure the default group using `az configure --defaults group=&amp;lt;name&amp;gt;`."
          },
          {
            "name": "Expand",
            "type": "string",
            "format": "--expand {value}",
            "help": "Specify the $expand query. Example: 'properties($select=deploymentProperties)'."
          }
        ]
      }
    },
    {
      "postfix": "ArtifactSourceList",
      "definiteArgument": "lab artifact-source list",
      "settingsClass": {
        "properties": [
          {
            "name": "LabName",
            "type": "string",
            "format": "--lab-name {value}",
            "help": "The name of the lab."
          },
          {
            "name": "ResourceGroup",
            "type": "string",
            "format": "--resource-group {value}",
            "help": "Name of resource group. You can configure the default group using `az configure --defaults group=&amp;lt;name&amp;gt;`."
          },
          {
            "name": "Expand",
            "type": "string",
            "format": "--expand {value}",
            "help": "Specify the $expand query. Example: 'properties($select=displayName)'."
          },
          {
            "name": "Filter",
            "type": "string",
            "format": "--filter {value}",
            "help": "The filter to apply to the operation."
          },
          {
            "name": "Orderby",
            "type": "string",
            "format": "--orderby {value}",
            "help": "The ordering expression for the results, using OData notation."
          },
          {
            "name": "Top",
            "type": "int",
            "format": "--top {value}",
            "help": "The maximum number of resources to return from the operation."
          }
        ]
      }
    },
    {
      "postfix": "ArtifactSourceShow",
      "definiteArgument": "lab artifact-source show",
      "settingsClass": {
        "properties": [
          {
            "name": "LabName",
            "type": "string",
            "format": "--lab-name {value}",
            "help": "The name of the lab."
          },
          {
            "name": "Name",
            "type": "string",
            "format": "--name {value}",
            "help": "The name of the artifact source."
          },
          {
            "name": "ResourceGroup",
            "type": "string",
            "format": "--resource-group {value}",
            "help": "Name of resource group. You can configure the default group using `az configure --defaults group=&amp;lt;name&amp;gt;`."
          },
          {
            "name": "Expand",
            "type": "string",
            "format": "--expand {value}",
            "help": "Specify the $expand query. Example: 'properties($select=displayName)'."
          }
        ]
      }
    },
    {
      "postfix": "VnetGet",
      "definiteArgument": "lab vnet get",
      "settingsClass": {
        "properties": [
          {
            "name": "LabName",
            "type": "string",
            "format": "--lab-name {value}",
            "help": "The name of the lab."
          },
          {
            "name": "Name",
            "type": "string",
            "format": "--name {value}",
            "help": "The name of the virtual network."
          },
          {
            "name": "ResourceGroup",
            "type": "string",
            "format": "--resource-group {value}",
            "help": "Name of resource group. You can configure the default group using `az configure --defaults group=&amp;lt;name&amp;gt;`."
          },
          {
            "name": "Expand",
            "type": "string",
            "format": "--expand {value}",
            "help": "Specify the $expand query. Example: 'properties($expand=externalSubnets)'."
          }
        ]
      }
    },
    {
      "postfix": "VnetList",
      "definiteArgument": "lab vnet list",
      "settingsClass": {
        "properties": [
          {
            "name": "LabName",
            "type": "string",
            "format": "--lab-name {value}",
            "help": "The name of the lab."
          },
          {
            "name": "ResourceGroup",
            "type": "string",
            "format": "--resource-group {value}",
            "help": "Name of resource group. You can configure the default group using `az configure --defaults group=&amp;lt;name&amp;gt;`."
          },
          {
            "name": "Expand",
            "type": "string",
            "format": "--expand {value}",
            "help": "Specify the $expand query. Example: 'properties($expand=externalSubnets)'."
          },
          {
            "name": "Filter",
            "type": "string",
            "format": "--filter {value}",
            "help": "The filter to apply to the operation."
          },
          {
            "name": "Orderby",
            "type": "string",
            "format": "--orderby {value}",
            "help": "The ordering expression for the results, using OData notation."
          },
          {
            "name": "Top",
            "type": "int",
            "format": "--top {value}",
            "help": "The maximum number of resources to return from the operation."
          }
        ]
      }
    },
    {
      "postfix": "SecretDelete",
      "definiteArgument": "lab secret delete",
      "settingsClass": {
        "properties": [
          {
            "name": "LabName",
            "type": "string",
            "format": "--lab-name {value}",
            "help": "The name of the lab."
          },
          {
            "name": "Name",
            "type": "string",
            "format": "--name {value}",
            "help": "The name of the secret."
          },
          {
            "name": "ResourceGroup",
            "type": "string",
            "format": "--resource-group {value}",
            "help": "Name of resource group. You can configure the default group using `az configure --defaults group=&amp;lt;name&amp;gt;`."
          }
        ]
      }
    },
    {
      "postfix": "SecretList",
      "definiteArgument": "lab secret list",
      "settingsClass": {
        "properties": [
          {
            "name": "LabName",
            "type": "string",
            "format": "--lab-name {value}",
            "help": "The name of the lab."
          },
          {
            "name": "ResourceGroup",
            "type": "string",
            "format": "--resource-group {value}",
            "help": "Name of resource group. You can configure the default group using `az configure --defaults group=&amp;lt;name&amp;gt;`."
          },
          {
            "name": "Expand",
            "type": "string",
            "format": "--expand {value}",
            "help": "Specify the $expand query. Example: 'properties($select=value)'."
          },
          {
            "name": "Filter",
            "type": "string",
            "format": "--filter {value}",
            "help": "The filter to apply to the operation."
          },
          {
            "name": "Orderby",
            "type": "string",
            "format": "--orderby {value}",
            "help": "The ordering expression for the results, using OData notation."
          },
          {
            "name": "Top",
            "type": "int",
            "format": "--top {value}",
            "help": "The maximum number of resources to return from the operation."
          }
        ]
      }
    },
    {
      "postfix": "SecretSet",
      "definiteArgument": "lab secret set",
      "settingsClass": {
        "properties": [
          {
            "name": "LabName",
            "type": "string",
            "format": "--lab-name {value}",
            "help": "Name of the lab."
          },
          {
            "name": "Name",
            "type": "string",
            "format": "--name {value}",
            "help": "Name of the secret."
          },
          {
            "name": "ResourceGroup",
            "type": "string",
            "format": "--resource-group {value}",
            "help": "Name of resource group. You can configure the default group using `az configure --defaults group=&amp;lt;name&amp;gt;`."
          },
          {
            "name": "Value",
            "type": "string",
            "format": "--value {value}",
            "help": "Value of the secret."
          }
        ]
      }
    },
    {
      "postfix": "SecretShow",
      "definiteArgument": "lab secret show",
      "settingsClass": {
        "properties": [
          {
            "name": "LabName",
            "type": "string",
            "format": "--lab-name {value}",
            "help": "The name of the lab."
          },
          {
            "name": "Name",
            "type": "string",
            "format": "--name {value}",
            "help": "The name of the secret."
          },
          {
            "name": "ResourceGroup",
            "type": "string",
            "format": "--resource-group {value}",
            "help": "Name of resource group. You can configure the default group using `az configure --defaults group=&amp;lt;name&amp;gt;`."
          },
          {
            "name": "Expand",
            "type": "string",
            "format": "--expand {value}",
            "help": "Specify the $expand query. Example: 'properties($select=value)'."
          }
        ]
      }
    },
    {
      "postfix": "ArtifactList",
      "definiteArgument": "lab artifact list",
      "settingsClass": {
        "properties": [
          {
            "name": "ArtifactSourceName",
            "type": "string",
            "format": "--artifact-source-name {value}",
            "help": "The name of the artifact source."
          },
          {
            "name": "LabName",
            "type": "string",
            "format": "--lab-name {value}",
            "help": "The name of the lab."
          },
          {
            "name": "ResourceGroup",
            "type": "string",
            "format": "--resource-group {value}",
            "help": "Name of resource group. You can configure the default group using `az configure --defaults group=&amp;lt;name&amp;gt;`."
          },
          {
            "name": "Expand",
            "type": "string",
            "format": "--expand {value}",
            "help": "Specify the $expand query. Example: 'properties($select=title)'."
          },
          {
            "name": "Filter",
            "type": "string",
            "format": "--filter {value}",
            "help": "The filter to apply to the operation."
          },
          {
            "name": "Orderby",
            "type": "string",
            "format": "--orderby {value}",
            "help": "The ordering expression for the results, using OData notation."
          },
          {
            "name": "Top",
            "type": "int",
            "format": "--top {value}",
            "help": "The maximum number of resources to return from the operation."
          }
        ]
      }
    },
    {
      "postfix": "ArmTemplateList",
      "definiteArgument": "lab arm-template list",
      "settingsClass": {
        "properties": [
          {
            "name": "ArtifactSourceName",
            "type": "string",
            "format": "--artifact-source-name {value}",
            "help": "The name of the artifact source."
          },
          {
            "name": "LabName",
            "type": "string",
            "format": "--lab-name {value}",
            "help": "The name of the lab."
          },
          {
            "name": "ResourceGroup",
            "type": "string",
            "format": "--resource-group {value}",
            "help": "Name of resource group. You can configure the default group using `az configure --defaults group=&amp;lt;name&amp;gt;`."
          },
          {
            "name": "Expand",
            "type": "string",
            "format": "--expand {value}",
            "help": "Specify the $expand query. Example: 'properties($select=displayName)'."
          },
          {
            "name": "Filter",
            "type": "string",
            "format": "--filter {value}",
            "help": "The filter to apply to the operation."
          },
          {
            "name": "Orderby",
            "type": "string",
            "format": "--orderby {value}",
            "help": "The ordering expression for the results, using OData notation."
          },
          {
            "name": "Top",
            "type": "int",
            "format": "--top {value}",
            "help": "The maximum number of resources to return from the operation."
          }
        ]
      }
    },
    {
      "postfix": "ArmTemplateShow",
      "definiteArgument": "lab arm-template show",
      "settingsClass": {
        "properties": [
          {
            "name": "ArtifactSourceName",
            "type": "string",
            "format": "--artifact-source-name {value}",
            "help": "Name of the artifact source."
          },
          {
            "name": "LabName",
            "type": "string",
            "format": "--lab-name {value}",
            "help": "Name of the lab."
          },
          {
            "name": "Name",
            "type": "string",
            "format": "--name {value}",
            "help": "Name of the Azure Resource Manager template."
          },
          {
            "name": "ResourceGroup",
            "type": "string",
            "format": "--resource-group {value}",
            "help": "Name of lab's resource group."
          },
          {
            "name": "ExportParameters",
            "type": "string",
            "format": "--export-parameters {value}",
            "help": "Whether or not to export parameters template."
          }
        ]
      }
    },
    {
      "postfix": "VmApplyArtifacts",
      "definiteArgument": "lab vm apply-artifacts",
      "settingsClass": {
        "properties": [
          {
            "name": "LabName",
            "type": "string",
            "format": "--lab-name {value}",
            "help": "Name of the Lab."
          },
          {
            "name": "Name",
            "type": "string",
            "format": "--name {value}",
            "help": "Name of the virtual machine."
          },
          {
            "name": "ResourceGroup",
            "type": "string",
            "format": "--resource-group {value}",
            "help": "Name of lab's resource group."
          },
          {
            "name": "Artifacts",
            "type": "string",
            "format": "--artifacts {value}",
            "help": "JSON encoded array of artifacts to be applied. Use '@{file}' to load from a file."
          }
        ]
      }
    },
    {
      "postfix": "VmClaim",
      "definiteArgument": "lab vm claim",
      "settingsClass": {
        "properties": [
          {
            "name": "LabName",
            "type": "string",
            "format": "--lab-name {value}",
            "help": "Name of the lab."
          },
          {
            "name": "Name",
            "type": "string",
            "format": "--name {value}",
            "help": "Name of the virtual machine to claim."
          },
          {
            "name": "ResourceGroup",
            "type": "string",
            "format": "--resource-group {value}",
            "help": "Name of lab's resource group."
          }
        ]
      }
    },
    {
      "postfix": "VmCreate",
      "definiteArgument": "lab vm create",
      "settingsClass": {
        "properties": [
          {
            "name": "LabName",
            "type": "string",
            "format": "--lab-name {value}",
            "help": "Name of the lab."
          },
          {
            "name": "Name",
            "type": "string",
            "format": "--name {value}",
            "help": "Name of the virtual machine."
          },
          {
            "name": "ResourceGroup",
            "type": "string",
            "format": "--resource-group {value}",
            "help": "Name of resource group. You can configure the default group using `az configure --defaults group=&amp;lt;name&amp;gt;`."
          },
          {
            "name": "AllowClaim",
            "type": "string",
            "format": "--allow-claim {value}",
            "help": "Flag indicating if the VM should be created as claimable."
          },
          {
            "name": "Artifacts",
            "type": "string",
            "format": "--artifacts {value}",
            "help": "JSON encoded array of artifacts to be applied. Use '@{file}' to load from a file."
          },
          {
            "name": "DiskType",
            "type": "string",
            "format": "--disk-type {value}",
            "help": "Storage type to use for virtual machine."
          },
          {
            "name": "ExpirationDate",
            "type": "string",
            "format": "--expiration-date {value}",
            "help": "The expiration date in UTC(YYYY-mm-dd) for the VM."
          },
          {
            "name": "Formula",
            "type": "string",
            "format": "--formula {value}",
            "help": "Name of the formula. Use `az lab formula list` for available formulas."
          },
          {
            "name": "GenerateSshKeys",
            "type": "string",
            "format": "--generate-ssh-keys {value}",
            "help": "Generate SSH public and private key files if missing."
          },
          {
            "name": "Image",
            "type": "string",
            "format": "--image {value}",
            "help": "The name of the operating system image (gallery image name or custom image name/ID)."
          },
          {
            "name": "ImageType",
            "type": "string",
            "format": "--image-type {value}",
            "help": "Type of the image. Allowed values are: gallery, custom."
          },
          {
            "name": "Notes",
            "type": "string",
            "format": "--notes {value}",
            "help": "Notes for the virtual machine."
          },
          {
            "name": "Size",
            "type": "string",
            "format": "--size {value}",
            "help": "The size of the VM to be created. See <a href=\"https://azure.microsoft.com/en-us/pricing/details/virtual-machines/\">https://azure.microsoft.com/en-us/pricing/details/virtual-machines/</a> for size info."
          },
          {
            "name": "Tags",
            "type": "string",
            "format": "--tags {value}",
            "help": "Space-separated tags in `key[=value]` format."
          },
          {
            "name": "AdminPassword",
            "type": "string",
            "format": "--admin-password {value}",
            "secret": true,
            "help": "Password for the VM admin."
          },
          {
            "name": "AdminUsername",
            "type": "string",
            "format": "--admin-username {value}",
            "help": "Username for the VM admin."
          },
          {
            "name": "AuthenticationType",
            "type": "string",
            "format": "--authentication-type {value}",
            "help": "Type of authentication allowed for the VM. Allowed values are: password, ssh."
          },
          {
            "name": "SavedSecret",
            "type": "string",
            "format": "--saved-secret {value}",
            "secret": true,
            "help": "Name of the saved secret to be used for authentication."
          },
          {
            "name": "SshKey",
            "type": "string",
            "format": "--ssh-key {value}",
            "help": "The SSH public key or public key file path. Use `--generate-ssh-keys` to generate SSH keys."
          },
          {
            "name": "IpConfiguration",
            "type": "string",
            "format": "--ip-configuration {value}",
            "help": "Type of IP configuration to use for the VM. Allowed values are: shared, public, private."
          },
          {
            "name": "Subnet",
            "type": "string",
            "format": "--subnet {value}",
            "help": "Name of the subnet to add the VM to."
          },
          {
            "name": "VnetName",
            "type": "string",
            "format": "--vnet-name {value}",
            "help": "Name of the virtual network to add the VM to."
          }
        ]
      }
    },
    {
      "postfix": "VmDelete",
      "definiteArgument": "lab vm delete",
      "settingsClass": {
        "properties": [
          {
            "name": "LabName",
            "type": "string",
            "format": "--lab-name {value}",
            "help": "The name of the lab."
          },
          {
            "name": "Name",
            "type": "string",
            "format": "--name {value}",
            "help": "The name of the virtual machine."
          },
          {
            "name": "ResourceGroup",
            "type": "string",
            "format": "--resource-group {value}",
            "help": "Name of resource group. You can configure the default group using `az configure --defaults group=&amp;lt;name&amp;gt;`."
          }
        ]
      }
    },
    {
      "postfix": "VmList",
      "definiteArgument": "lab vm list",
      "settingsClass": {
        "properties": [
          {
            "name": "LabName",
            "type": "string",
            "format": "--lab-name {value}",
            "help": "Name of the lab."
          },
          {
            "name": "ResourceGroup",
            "type": "string",
            "format": "--resource-group {value}",
            "help": "Name of resource group. You can configure the default group using `az configure --defaults group=&amp;lt;name&amp;gt;`."
          },
          {
            "name": "All",
            "type": "string",
            "format": "--all {value}",
            "help": "List all virtual machines in the lab. Cannot be used with `--filters`."
          },
          {
            "name": "Claimable",
            "type": "string",
            "format": "--claimable {value}",
            "help": "List only claimable virtual machines in the lab. Cannot be used with `--filters`."
          },
          {
            "name": "Expand",
            "type": "string",
            "format": "--expand {value}",
            "help": "The expand query."
          },
          {
            "name": "ObjectId",
            "type": "string",
            "format": "--object-id {value}",
            "help": "Object ID of the owner to list VMs for."
          },
          {
            "name": "OrderBy",
            "type": "string",
            "format": "--order-by {value}",
            "help": "The ordering expression for the results using OData notation."
          },
          {
            "name": "Top",
            "type": "int",
            "format": "--top {value}",
            "help": "The maximum number of resources to return."
          },
          {
            "name": "Environment",
            "type": "string",
            "format": "--environment {value}",
            "help": "Name or ID of the environment to list virtual machines in. Cannot be used with `--filters`."
          },
          {
            "name": "Filters",
            "type": "string",
            "format": "--filters {value}",
            "help": "The filter to apply."
          }
        ]
      }
    },
    {
      "postfix": "VmShow",
      "definiteArgument": "lab vm show",
      "settingsClass": {
        "properties": [
          {
            "name": "LabName",
            "type": "string",
            "format": "--lab-name {value}",
            "help": "The name of the lab."
          },
          {
            "name": "Name",
            "type": "string",
            "format": "--name {value}",
            "help": "The name of the virtual machine."
          },
          {
            "name": "ResourceGroup",
            "type": "string",
            "format": "--resource-group {value}",
            "help": "Name of resource group. You can configure the default group using `az configure --defaults group=&amp;lt;name&amp;gt;`."
          },
          {
            "name": "Expand",
            "type": "string",
            "format": "--expand {value}",
            "help": "Specify the $expand query. Example: 'properties($expand=artifacts,computeVm,networkInterface,applicableSchedule)'."
          }
        ]
      }
    },
    {
      "postfix": "VmStart",
      "definiteArgument": "lab vm start",
      "settingsClass": {
        "properties": [
          {
            "name": "LabName",
            "type": "string",
            "format": "--lab-name {value}",
            "help": "The name of the lab."
          },
          {
            "name": "Name",
            "type": "string",
            "format": "--name {value}",
            "help": "The name of the virtual machine."
          },
          {
            "name": "ResourceGroup",
            "type": "string",
            "format": "--resource-group {value}",
            "help": "Name of resource group. You can configure the default group using `az configure --defaults group=&amp;lt;name&amp;gt;`."
          }
        ]
      }
    },
    {
      "postfix": "VmStop",
      "definiteArgument": "lab vm stop",
      "settingsClass": {
        "properties": [
          {
            "name": "LabName",
            "type": "string",
            "format": "--lab-name {value}",
            "help": "The name of the lab."
          },
          {
            "name": "Name",
            "type": "string",
            "format": "--name {value}",
            "help": "The name of the virtual machine."
          },
          {
            "name": "ResourceGroup",
            "type": "string",
            "format": "--resource-group {value}",
            "help": "Name of resource group. You can configure the default group using `az configure --defaults group=&amp;lt;name&amp;gt;`."
          }
        ]
      }
    },
    {
      "postfix": "GalleryImageList",
      "definiteArgument": "lab gallery-image list",
      "settingsClass": {
        "properties": [
          {
            "name": "LabName",
            "type": "string",
            "format": "--lab-name {value}",
            "help": "The name of the lab."
          },
          {
            "name": "ResourceGroup",
            "type": "string",
            "format": "--resource-group {value}",
            "help": "Name of resource group. You can configure the default group using `az configure --defaults group=&amp;lt;name&amp;gt;`."
          },
          {
            "name": "Expand",
            "type": "string",
            "format": "--expand {value}",
            "help": "Specify the $expand query. Example: 'properties($select=author)'."
          },
          {
            "name": "Filter",
            "type": "string",
            "format": "--filter {value}",
            "help": "The filter to apply to the operation."
          },
          {
            "name": "Orderby",
            "type": "string",
            "format": "--orderby {value}",
            "help": "The ordering expression for the results, using OData notation."
          },
          {
            "name": "Top",
            "type": "int",
            "format": "--top {value}",
            "help": "The maximum number of resources to return from the operation."
          }
        ]
      }
    },
    {
      "postfix": "FormulaDelete",
      "definiteArgument": "lab formula delete",
      "settingsClass": {
        "properties": [
          {
            "name": "LabName",
            "type": "string",
            "format": "--lab-name {value}",
            "help": "The name of the lab."
          },
          {
            "name": "Name",
            "type": "string",
            "format": "--name {value}",
            "help": "The name of the formula."
          },
          {
            "name": "ResourceGroup",
            "type": "string",
            "format": "--resource-group {value}",
            "help": "Name of resource group. You can configure the default group using `az configure --defaults group=&amp;lt;name&amp;gt;`."
          }
        ]
      }
    },
    {
      "postfix": "FormulaExportArtifacts",
      "definiteArgument": "lab formula export-artifacts",
      "settingsClass": {
        "properties": [
          {
            "name": "LabName",
            "type": "string",
            "format": "--lab-name {value}",
            "help": "Name of the lab."
          },
          {
            "name": "Name",
            "type": "string",
            "format": "--name {value}",
            "help": "Name of the formula."
          },
          {
            "name": "ResourceGroup",
            "type": "string",
            "format": "--resource-group {value}",
            "help": "Name of resource group. You can configure the default group using `az configure --defaults group=&amp;lt;name&amp;gt;`."
          }
        ]
      }
    },
    {
      "postfix": "FormulaList",
      "definiteArgument": "lab formula list",
      "settingsClass": {
        "properties": [
          {
            "name": "LabName",
            "type": "string",
            "format": "--lab-name {value}",
            "help": "The name of the lab."
          },
          {
            "name": "ResourceGroup",
            "type": "string",
            "format": "--resource-group {value}",
            "help": "Name of resource group. You can configure the default group using `az configure --defaults group=&amp;lt;name&amp;gt;`."
          },
          {
            "name": "Expand",
            "type": "string",
            "format": "--expand {value}",
            "help": "Specify the $expand query. Example: 'properties($select=description)'."
          },
          {
            "name": "Filter",
            "type": "string",
            "format": "--filter {value}",
            "help": "The filter to apply to the operation."
          },
          {
            "name": "Orderby",
            "type": "string",
            "format": "--orderby {value}",
            "help": "The ordering expression for the results, using OData notation."
          },
          {
            "name": "Top",
            "type": "int",
            "format": "--top {value}",
            "help": "The maximum number of resources to return from the operation."
          }
        ]
      }
    },
    {
      "postfix": "FormulaShow",
      "definiteArgument": "lab formula show",
      "settingsClass": {
        "properties": [
          {
            "name": "LabName",
            "type": "string",
            "format": "--lab-name {value}",
            "help": "Name of the lab."
          },
          {
            "name": "Name",
            "type": "string",
            "format": "--name {value}",
            "help": "Name of the formula."
          },
          {
            "name": "ResourceGroup",
            "type": "string",
            "format": "--resource-group {value}",
            "help": "Name of resource group. You can configure the default group using `az configure --defaults group=&amp;lt;name&amp;gt;`."
          },
          {
            "name": "Expand",
            "type": "string",
            "format": "--expand {value}",
            "help": "Specify the $expand query. Example: 'properties($select=description)'."
          }
        ]
      }
    }
  ],
  "commonTaskProperties": [
    {
      "name": "Debug",
      "type": "string",
      "format": "--debug {value}",
      "help": "Increase logging verbosity to show all debug logs."
    },
    {
      "name": "Help",
      "type": "string",
      "format": "--help {value}",
      "help": "Show this help message and exit."
    },
    {
      "name": "Output",
      "type": "AzureOutput",
      "format": "--output {value}",
      "help": "Output format."
    },
    {
      "name": "Query",
      "type": "string",
      "format": "--query {value}",
      "help": "JMESPath query string. See <a href=\"http://jmespath.org/\">http://jmespath.org/</a> for more information and examples."
    },
    {
      "name": "Verbose",
      "type": "string",
      "format": "--verbose {value}",
      "help": "Increase logging verbosity. Use --debug for full debug logs."
    }
  ]
}